CHANGELOG.txt
LICENSE.txt
MANIFEST.in
README.txt
__init__.py
setup.py
database/database.py
env/envVars.py
kanwarFYPCMS.egg-info/PKG-INFO
kanwarFYPCMS.egg-info/SOURCES.txt
kanwarFYPCMS.egg-info/dependency_links.txt
kanwarFYPCMS.egg-info/requires.txt
kanwarFYPCMS.egg-info/top_level.txt
tabs/page1/attendance/attendance.py
tabs/page2/department/department.py
tabs/page2/report/report.py
tabs/page2/result/result.py
tabs/page2/result/toplevel/test/test.py
tabs/page2/session/sessions.py
tabs/page2/staff/staff.py
tabs/page2/student/student.py
tools/form/Form.py
tools/login/Login.py
tools/messagebox/MessageBox.py
tools/signup/SignUp.py
tools/tooltip/ToolTip.py
validator/authenticate.py