Metadata-Version: 2.1
Name: kanwarFYPCMS
Version: 0.0.1
Summary: This is my CMS for FYP in GCS
Home-page: 
Author: Kanwar Adnan
Author-email: kanwaradnanrajput@gmail.com
License: MIT
Keywords: kanwarFYPCMS
Platform: UNKNOWN
Classifier: Development Status :: 5 - Production/Stable
Classifier: Intended Audience :: Education
Classifier: Operating System :: Microsoft :: Windows :: Windows 10
Classifier: License :: OSI Approved :: MIT License
Classifier: Programming Language :: Python :: 3
License-File: LICENSE.txt
